xdcheckin/__init__.py
xdcheckin/__main__.py
xdcheckin/core/__init__.py
xdcheckin/core/chaoxing.py
xdcheckin/core/classrooms.py
xdcheckin/core/cldisk.py
xdcheckin/core/locations.py
xdcheckin/core/xidian.py
xdcheckin/server/__init__.py
xdcheckin/server/server.py
xdcheckin/server/static/activity.js
xdcheckin/server/static/classroom.js
xdcheckin/server/static/curriculum.js
xdcheckin/server/static/g_classroom_urls.js
xdcheckin/server/static/g_locations.js
xdcheckin/server/static/global.js
xdcheckin/server/static/location.js
xdcheckin/server/static/login.js
xdcheckin/server/static/player.js
xdcheckin/server/static/polyfill.js
xdcheckin/server/static/style.css
xdcheckin/server/static/util.js
xdcheckin/server/templates/index.html
xdcheckin/util/__init__.py
xdcheckin/util/captcha.py
xdcheckin/util/encryption.py
xdcheckin/util/image.py
xdcheckin/util/network.py
xdcheckin/util/session.py
xdcheckin/util/time.py
xdcheckin/util/types.py
xdcheckin/util/version.py
xdcheckin/util/web.py
xdcheckin-4.2.3.dist-info/licenses/LICENSE
xdcheckin-4.2.3.dist-info/METADATA
xdcheckin-4.2.3.dist-info/WHEEL
xdcheckin-4.2.3.dist-info/entry_points.txt
xdcheckin-4.2.3.dist-info/top_level.txt
xdcheckin-4.2.3.dist-info/RECORD
