Metadata-Version: 2.4
Name: Xdcheckin
Version: 4.2.3
Summary: Chaoxing Checkin Tool for XDU.
Author-email: Pairman <pairmanxlr@gmail.com>
License: GNU General Public License v3 (GPLv3)
Project-URL: Homepage, https://github.com/Pairman/Xdcheckin
Project-URL: Changelog, https://github.com/Pairman/Xdcheckin/blob/main/CHANGELOG.md
Keywords: xdu,xidian,chaoxing,livestream
Classifier: Framework :: aiohttp
Classifier: Programming Language :: Python :: 3
Classifier: Programming Language :: JavaScript
Classifier: License :: OSI Approved :: GNU General Public License (GPL)
Requires-Python: >=3.8
License-File: LICENSE
Requires-Dist: aiocache>=0.12.0
Requires-Dist: aiohttp>=3.8.1
Requires-Dist: aiohttp-compress>=0.2.0
Requires-Dist: aiohttp-session>=2.6.0
Requires-Dist: pillow>=8.4.0
Requires-Dist: pycryptodome>=3.9.4
Requires-Dist: yarl>=1.12.0
Provides-Extra: image
Requires-Dist: pyzbar>=0.1.8; extra == "image"
Requires-Dist: xdcheckin-ffmpeg>=1.0.0; extra == "image"
Dynamic: license-file
